LICENSE
MANIFEST.in
README.markdown
setup.py
tests.py
bertrpc/__init__.py
bertrpc/client.py
bertrpc/error.py
bertrpc.egg-info/PKG-INFO
bertrpc.egg-info/SOURCES.txt
bertrpc.egg-info/dependency_links.txt
bertrpc.egg-info/requires.txt
bertrpc.egg-info/top_level.txt