Metadata-Version: 1.0
Name: bertrpc
Version: 0.1.1
Summary: BERT-RPC Library
Home-page: http://github.com/mjrusso/python-bertrpc
Author: Michael J. Russo
Author-email: mjrusso@gmail.com
License: MIT
Platform: UNKNOWN
Classifier: Intended Audience :: Developers
Classifier: Operating System :: OS Independent
Classifier: Programming Language :: Python
Classifier: Topic :: Software Development :: Libraries :: Python Modules
